qary/__init__.py
qary/actions/osm.py
qary/chat/__init__.py
qary/chat/classifiers.py
qary/chat/dialog.py
qary/chat/dialog_engine.py
qary/chat/dialog_managers.py
qary/chat/dialog_new.py
qary/chat/dialog_parse.py
qary/chat/intents.py
qary/chat/matchers.py
qary/chat/quiz_skill.py
qary/chat/understanders.py
qary/chat/v2.py
qary/chat/v3.py
qary/chat/v4.py
qary/clibot.py
qary/config.py
qary/constants.py
qary/data/__init__.py
qary/data/book_smarts/README.md
qary/data/book_smarts/aima-1-0-2.yml
qary/data/book_smarts/book_club_discussion_question_templates.yml
qary/data/book_smarts/discussion_questions.txt
qary/data/chat/example-multilingual.v3.dialog.yml
qary/data/chat/example-multilingual.v4.dialog.yml
qary/data/chat/moia-poly-dialog-tree-simplified-chinese.v3.dialog.yml
qary/data/constants/__init__.py
qary/data/constants/emoticons-from-wikipedia.csv
qary/data/constants/nltk_stopwords_english.json
qary/data/constants/nltk_stopwords_english.py
qary/data/constants/tlds-from-iana.csv
qary/data/constants/uri-schemes.xhtml.csv
qary/data/corpora/Evolution of AI Timeline History.md
qary/data/corpora/README.md
qary/data/corpora/rss_feeds/hidden-brain-june-podcasts.xml
qary/data/corpora/schmidt-futures-tools-competition-finalists.yml
qary/data/corpora/scifi_novel_title_authors.csv
qary/data/corpora/sentences-conversational-questions.yml
qary/data/corpora/sentences.yml
qary/data/corpora/spelling_corrector_word_count.gz
qary/data/corpora/web_pages/Competition Finalists – Futures Forum.html
qary/data/corpora/web_pages/Tools Competition Catalyze Winners – Futures Forum.html
qary/data/corpora/web_pages/Tools Competition Winners -- Futures Forum.html
qary/data/corpora/wikipedia/README.md
qary/data/corpora/wikipedia/george_floyd_karma.yml
qary/data/datasets.yml
qary/data/downloadable_bigdata_directory.yml
qary/data/eliza_doctor.txt
qary/data/factquest/critical-thinking-problemm-solving-logic.yml
qary/data/factquest/default-text-adventure-messages.yml
qary-0.7.27.dist-info/entry_points.txt
qary-0.7.27.dist-info/LICENSE
qary-0.7.27.dist-info/WHEEL
qary-0.7.27.dist-info/METADATA
qary-0.7.27.dist-info/RECORD
