Metadata-Version: 2.1
Name: qary
Version: 0.7.27
Summary: A chatbot that assists rather than manipulates.
Home-page: https://gitlab.com/tangibleai/qary
License: MIT
Author: ProAI
Author-email: hobs@proai.org
Requires-Python: >=3.8.3,<4
Classifier: Development Status :: 3 - Alpha
Classifier: Intended Audience :: Developers
Classifier: License :: OSI Approved :: MIT License
Classifier: Operating System :: OS Independent
Classifier: Programming Language :: Python :: 3
Classifier: Programming Language :: Python :: 3.9
Classifier: Programming Language :: Python :: 3.10
Classifier: Programming Language :: Python :: 3.11
Classifier: Topic :: Software Development :: Libraries :: Python Modules
Requires-Dist: Django (>=4.1,<5.0)
Requires-Dist: PyPDF2 (>=2.1.0,<3.0.0)
Requires-Dist: babel (>=2.11.0,<3.0.0)
Requires-Dist: beautifulsoup4 (>=4.11,<5.0)
Requires-Dist: bidict (>=0.22,<0.23)
Requires-Dist: bleach (>=5.0,<6.0)
Requires-Dist: boto3 (>=1.26,<2.0)
Requires-Dist: botocore (>=1.29,<2.0)
Requires-Dist: configargparse (>=1.5,<2.0)
Requires-Dist: cython (>=0.29,<0.30)
Requires-Dist: dataframe-image (>=0.1,<0.2)
Requires-Dist: edit-distance (>=1.0,<2.0)
Requires-Dist: elasticsearch (>=8.5,<9.0)
Requires-Dist: environment (>=1.0,<2.0)
Requires-Dist: gitpython (>=3.1,<4.0)
Requires-Dist: graphviz (>=0.20,<0.21)
Requires-Dist: h5py (>=3.7.0,<4.0.0)
Requires-Dist: html2text (>=2020.1.16,<2021.0.0)
Requires-Dist: html5lib (>=1.1,<2.0)
Requires-Dist: huggingface-hub (>=0.11.0,<0.12.0)
Requires-Dist: jupyter-console (>=6.4.4)
Requires-Dist: lxml (>=4.9.1,<5.0.0)
Requires-Dist: m2r (>=0.3,<0.4)
Requires-Dist: matplotlib (>=3.6,<4.0)
Requires-Dist: matplotlib-inline (>=0.1,<0.2)
Requires-Dist: meilisearch (>=0.22.2,<0.23.0)
Requires-Dist: mistune (>=0.8.4,<0.9.0)
Requires-Dist: nltk (>=3.7,<4.0)
Requires-Dist: pandas (>=1.1,<2.0)
Requires-Dist: pillow (>=9.3.0,<10.0.0)
Requires-Dist: pip (>=22.3.1)
Requires-Dist: poetry (>=1,<2)
Requires-Dist: pronouncing (>=0.2.0,<0.3.0)
Requires-Dist: psutil (>=5.9.4,<6.0.0)
Requires-Dist: python-dotenv (>=0.13.0,<0.14.0)
Requires-Dist: python-slugify (>=7.0.0,<8.0.0)
Requires-Dist: pyyaml (>=6.0,<7.0)
Requires-Dist: rapidfuzz (>=2.13.2)
Requires-Dist: recommonmark (>=0.7,<0.8)
Requires-Dist: scikit-image (>=0.19.3)
Requires-Dist: scikit-learn (>=1.1.3)
Requires-Dist: scipy (>=1.9.3)
Requires-Dist: seaborn (>=0.11.2,<0.12.0)
Requires-Dist: sentence_transformers (>=2.2,<3.0)
Requires-Dist: spacy (==3.2.4)
Requires-Dist: sphinx (>=5.3,<6.0)
Requires-Dist: torch (>=1.13,<2.0)
Requires-Dist: torchtext (>=0.14,<0.15)
Requires-Dist: tox (>=3.25.0,<4.0.0)
Requires-Dist: tqdm (>=4.64,<5.0)
Requires-Dist: unidecode (>=1.3,<2.0)
Requires-Dist: wikipedia (>=1.4,<2.0)
Project-URL: Repository, https://gitlab.com/tangibleai/qary
